epocsecs
