Metadata-Version: 1.0
Name: epocsecs
Version: 1.0.1
Summary: a quick utility to generate epocsecs
Home-page: https://github.com/joranbeasley/epocsecs
Author: joran
Author-email: joranbeasley@gmail.com
License: MIT
Platform: UNKNOWN
